sciencespy/__init__.py
sciencespy/bem.py
sciencespy/cal.py
sciencespy/city3d.py
sciencespy/cosim.py
sciencespy/dom.py
sciencespy/irim.py
sciencespy/umm.py
sciencespy/utils.py
sciencespy-1.0.0.dist-info/LICENSE.txt
sciencespy-1.0.0.dist-info/METADATA
sciencespy-1.0.0.dist-info/WHEEL
sciencespy-1.0.0.dist-info/top_level.txt
sciencespy-1.0.0.dist-info/RECORD
