Metadata-Version: 2.1
Name: sciencespy
Version: 1.0.0
Summary: Python code developed during the SCIENCES project
Home-page: https://github.com/tudelft3d/SCIENCES
Author: Miguel Martin Fehlmann
Author-email: M.Martin@tudelft.nl
Project-URL: Source, https://github.com/tudelft3d/SCIENCES/sciencespy
Classifier: Development Status :: 3 - Alpha
Classifier: Intended Audience :: Developers
Classifier: Topic :: Software Development :: Build Tools
Classifier: License :: OSI Approved :: GNU General Public License (GPL)
Classifier: Programming Language :: Python :: 3.7
Requires-Python: >=3.7
License-File: LICENSE.txt
